sshler/__init__.py
sshler/cli.py
sshler/config.py
sshler/ssh.py
sshler/ssh_config.py
sshler/state.py
sshler/webapp.py
sshler/scripts/install-sshler-task.ps1
sshler/scripts/remove-sshler-task.ps1
sshler/scripts/run-sshler.ps1
sshler/static/base.js
sshler/static/favicon-terminal.svg
sshler/static/favicon.svg
sshler/static/file-edit.js
sshler/static/file-view.js
sshler/static/style.css
sshler/static/term.js
sshler/templates/base.html
sshler/templates/box.html
sshler/templates/docs.html
sshler/templates/file_edit.html
sshler/templates/file_view.html
sshler/templates/index.html
sshler/templates/new_box.html
sshler/templates/term.html
sshler/templates/partials/dir_listing.html
sshler-0.3.2.dist-info/METADATA
sshler-0.3.2.dist-info/WHEEL
sshler-0.3.2.dist-info/entry_points.txt
sshler-0.3.2.dist-info/top_level.txt
sshler-0.3.2.dist-info/RECORD
