Metadata-Version: 2.4
Name: sshler
Version: 0.3.2
Summary: A local FastAPI-powered SSH multiplexer for tmux-in-browser — from your laptop only.
Author: You
License-Expression: MIT
Project-URL: Homepage, https://github.com/gabu-quest/sshler
Project-URL: Repository, https://github.com/gabu-quest/sshler
Project-URL: Issues, https://github.com/gabu-quest/sshler/issues
Keywords: ssh,tmux,fastapi,sftp,htmx
Classifier: Development Status :: 3 - Alpha
Classifier: Environment :: Console
Classifier: Environment :: Web Environment
Classifier: Intended Audience :: Developers
Classifier: Operating System :: OS Independent
Classifier: Programming Language :: Python :: 3
Classifier: Programming Language :: Python :: 3 :: Only
Classifier: Programming Language :: Python :: 3.10
Classifier: Programming Language :: Python :: 3.11
Classifier: Programming Language :: Python :: 3.12
Classifier: Topic :: System :: Systems Administration
Classifier: Framework :: FastAPI
Requires-Python: >=3.12
Requires-Dist: fastapi>=0.115.0
Requires-Dist: uvicorn[standard]>=0.30.0
Requires-Dist: jinja2>=3.1
Requires-Dist: pyyaml>=6.0
Requires-Dist: asyncssh>=2.14.0
Requires-Dist: platformdirs>=4.2
Requires-Dist: pydantic>=2.7
Requires-Dist: python-multipart>=0.0.9
Requires-Dist: sqler>=1.2025.9.24
Provides-Extra: dev
Requires-Dist: anyio>=4.4; extra == "dev"
Requires-Dist: httpx>=0.27.0; extra == "dev"
Requires-Dist: pytest>=8.2; extra == "dev"
Requires-Dist: pytest-asyncio>=0.23; extra == "dev"
Requires-Dist: ruff>=0.5.6; extra == "dev"
